dash_cam/DashCam.py
dash_cam/__init__.py
dash_cam/_imports_.py
dash_cam/dash_cam.min.js
dash_cam/dash_cam.min.js.map
dash_cam/metadata.json
dash_cam/package-info.json
dash_cam-0.0.1.dist-info/LICENSE
dash_cam-0.0.1.dist-info/METADATA
dash_cam-0.0.1.dist-info/WHEEL
dash_cam-0.0.1.dist-info/top_level.txt
dash_cam-0.0.1.dist-info/RECORD
